{"totalAscensions":0,"cumulativeTotalRuns":12,"totalRuns":12,"cumulativeTotalDeaths":4,"dungeonData":[{"dungeonID":0,"maxFloorReached":13,"totalRunsPerDungeon":12,"deaths":4,"bestTimeToCompleteDungeon":3.4028234663852887e38,"runsToCompleteDungeonForTheFirstTime":0}],"completedDungeons":[],"hardcoreModeEnabled":false,"relaxedModeEnabled":false,"allowPause":true,"soulStones":2984,"soulStonesOnLastVisit":0,"ascendantShards":0,"disabled":false,"initialized":true,"notifications":12,"skillSlots":[{"_skillHashId":-1,"_slotIndex":0},{"_skillHashId":-1,"_slotIndex":1},{"_skillHashId":-1,"_slotIndex":2},{"_skillHashId":-1,"_slotIndex":3},{"_skillHashId":-1,"_slotIndex":4}],"narrativeEntriesData":[{"hashID":0,"executedInteractions":["Narrative_CAFirstTalk_Interaction01"]},{"hashID":1,"executedInteractions":["Narrative_CAOneLiners_Interaction01"]},{"hashID":2,"executedInteractions":["Narrative_CJDefeat_Interaction01"]},{"hashID":3,"executedInteractions":["Narrative_CJFirstTalk_Interaction01"]},{"hashID":4,"executedInteractions":[]},{"hashID":5,"executedInteractions":[]},{"hashID":6,"executedInteractions":["Narrative_JACageOpen_Interaction01"]},{"hashID":7,"executedInteractions":["Narrative_JACageReach_Interaction01"]},{"hashID":8,"executedInteractions":["Narrative_JAFirstTalk_Interaction01"]},{"hashID":9,"executedInteractions":["Narrative_JARescueFloor_Interaction01"]},{"hashID":10,"executedInteractions":[]},{"hashID":11,"executedInteractions":["Narrative_JAUnlockBell_Interaction01"]},{"hashID":12,"executedInteractions":["Narrative_JAWood_Interaction01"]},{"hashID":13,"executedInteractions":["Narrative_BrokenStairs_Interaction01"]},{"hashID":15,"executedInteractions":[]},{"hashID":16,"executedInteractions":["Narrative_FirstLevelUp_Interaction01"]},{"hashID":17,"executedInteractions":["Narrative_FirstRelic_Interaction01"]},{"hashID":18,"executedInteractions":["Narrative_Act1FirstRun_Interaction01","Narrative_Act1FirstRun_Interaction02"]},{"hashID":19,"executedInteractions":["Narrative_GameStart_Interaction01"]},{"hashID":20,"executedInteractions":["Narrative_ImportantItem_Interaction03"]},{"hashID":21,"executedInteractions":[]},{"hashID":22,"executedInteractions":["Narrative_PajeuOneLiners_Interaction01","Narrative_PajeuOneLiners_Interaction02","Narrative_PajeuOneLiners_Interaction03","Narrative_PajeuOneLiners_Interaction04","Narrative_PajeuOneLiners_Interaction05","Narrative_PajeuOneLiners_Interaction06","Narrative_PajeuOneLiners_Interaction07","Narrative_PajeuOneLiners_Interaction08"]},{"hashID":24,"executedInteractions":[]},{"hashID":25,"executedInteractions":[]},{"hashID":26,"executedInteractions":[]},{"hashID":27,"executedInteractions":["Narrative_JABellReminder_Interaction01"]},{"hashID":30,"executedInteractions":[]},{"hashID":31,"executedInteractions":[]},{"hashID":32,"executedInteractions":[]},{"hashID":36,"executedInteractions":[]},{"hashID":37,"executedInteractions":[]},{"hashID":38,"executedInteractions":[]},{"hashID":39,"executedInteractions":[]},{"hashID":40,"executedInteractions":[]},{"hashID":41,"executedInteractions":[]},{"hashID":43,"executedInteractions":[]},{"hashID":44,"executedInteractions":[]},{"hashID":45,"executedInteractions":[]},{"hashID":46,"executedInteractions":[]},{"hashID":47,"executedInteractions":[]},{"hashID":48,"executedInteractions":[]},{"hashID":49,"executedInteractions":[]},{"hashID":50,"executedInteractions":[]},{"hashID":52,"executedInteractions":[]},{"hashID":53,"executedInteractions":[]},{"hashID":55,"executedInteractions":[]},{"hashID":60,"executedInteractions":[]},{"hashID":63,"executedInteractions":[]},{"hashID":64,"executedInteractions":[]},{"hashID":66,"executedInteractions":[]},{"hashID":71,"executedInteractions":[]},{"hashID":74,"executedInteractions":[]},{"hashID":75,"executedInteractions":[]},{"hashID":76,"executedInteractions":[]},{"hashID":77,"executedInteractions":[]},{"hashID":78,"executedInteractions":[]},{"hashID":79,"executedInteractions":[]},{"hashID":80,"executedInteractions":[]},{"hashID":81,"executedInteractions":[]},{"hashID":82,"executedInteractions":[]},{"hashID":83,"executedInteractions":[]},{"hashID":85,"executedInteractions":[]},{"hashID":86,"executedInteractions":[]},{"hashID":90,"executedInteractions":[]},{"hashID":91,"executedInteractions":[]},{"hashID":92,"executedInteractions":[]},{"hashID":93,"executedInteractions":[]},{"hashID":94,"executedInteractions":[]},{"hashID":95,"executedInteractions":[]},{"hashID":98,"executedInteractions":[]},{"hashID":99,"executedInteractions":[]},{"hashID":100,"executedInteractions":[]},{"hashID":101,"executedInteractions":[]},{"hashID":102,"executedInteractions":[]},{"hashID":103,"executedInteractions":[]},{"hashID":104,"executedInteractions":[]},{"hashID":105,"executedInteractions":[]},{"hashID":106,"executedInteractions":[]},{"hashID":107,"executedInteractions":[]},{"hashID":108,"executedInteractions":[]},{"hashID":109,"executedInteractions":[]},{"hashID":111,"executedInteractions":[]},{"hashID":112,"executedInteractions":[]},{"hashID":114,"executedInteractions":["Narrative_BurrowerEncounter_Interaction01"]},{"hashID":115,"executedInteractions":[]},{"hashID":117,"executedInteractions":["Narrative_Cave1stRun_Interaction01"]},{"hashID":119,"executedInteractions":[]},{"hashID":120,"executedInteractions":["Narrative_Timer10seconds_Interaction01"]},{"hashID":121,"executedInteractions":["Narrative_Timer30seconds_Interaction01"]},{"hashID":122,"executedInteractions":["Narrative_HC1stRespawn_Interaction01"]},{"hashID":123,"executedInteractions":[]},{"hashID":124,"executedInteractions":[]},{"hashID":125,"executedInteractions":["Narrative_HC2ndRespawn_Interaction01"]},{"hashID":126,"executedInteractions":["Narrative_CACJDefeat_Interaction01"]},{"hashID":127,"executedInteractions":["Narrative_CAUnlockBell_Interaction01"]},{"hashID":129,"executedInteractions":[]},{"hashID":130,"executedInteractions":[]},{"hashID":131,"executedInteractions":[]},{"hashID":132,"executedInteractions":[]},{"hashID":133,"executedInteractions":[]},{"hashID":135,"executedInteractions":[]},{"hashID":136,"executedInteractions":[]},{"hashID":137,"executedInteractions":[]},{"hashID":138,"executedInteractions":[]},{"hashID":139,"executedInteractions":[]},{"hashID":140,"executedInteractions":[]},{"hashID":141,"executedInteractions":[]},{"hashID":142,"executedInteractions":[]},{"hashID":143,"executedInteractions":[]},{"hashID":144,"executedInteractions":[]},{"hashID":145,"executedInteractions":[]},{"hashID":146,"executedInteractions":[]},{"hashID":147,"executedInteractions":[]},{"hashID":148,"executedInteractions":[]},{"hashID":149,"executedInteractions":[]},{"hashID":150,"executedInteractions":[]},{"hashID":151,"executedInteractions":[]},{"hashID":152,"executedInteractions":[]},{"hashID":153,"executedInteractions":["Narrative_CJIntro_Interaction01"]},{"hashID":155,"executedInteractions":["Narrative_CAAfterJARescue_Interaction01"]},{"hashID":156,"executedInteractions":["Narrative_DungeonAfterJARescue_Interaction01"]},{"hashID":157,"executedInteractions":["Narrative_CJSecondTalk_Interaction01"]},{"hashID":158,"executedInteractions":["Narrative_DungeonAfterCJDefeat_Interaction01"]},{"hashID":159,"executedInteractions":[]},{"hashID":160,"executedInteractions":["Narrative_AfterBell_Interaction01"]},{"hashID":161,"executedInteractions":["Narrative_GameStart2_Interaction01","Narrative_GameStart2_Interaction02"]},{"hashID":167,"executedInteractions":["Narrative_JAafterBlessingOnboarding_Interaction01"]},{"hashID":168,"executedInteractions":["Narrative_EnterHouse_Interaction01"]},{"hashID":169,"executedInteractions":[]},{"hashID":170,"executedInteractions":["Narrative_Timer10secondsSecondTime_Interaction01"]},{"hashID":171,"executedInteractions":["Narrative_Timer30secondsSecondTime_Interaction01"]},{"hashID":172,"executedInteractions":["Narrative_Timer60secondsSecondTime_Interaction01"]},{"hashID":173,"executedInteractions":["Narrative_Timer60seconds_Interaction01"]},{"hashID":174,"executedInteractions":["Narrative_RescueSurvivalEnd_Interaction01"]},{"hashID":175,"executedInteractions":["Narrative_SurvivalCaveStart_Interaction01"]},{"hashID":177,"executedInteractions":[]},{"hashID":178,"executedInteractions":["Narrative_RescueSurvival2ndRunEnd_Interaction01"]},{"hashID":179,"executedInteractions":[]},{"hashID":180,"executedInteractions":[]},{"hashID":184,"executedInteractions":[]},{"hashID":185,"executedInteractions":[]},{"hashID":186,"executedInteractions":[]},{"hashID":187,"executedInteractions":[]},{"hashID":188,"executedInteractions":[]},{"hashID":189,"executedInteractions":[]},{"hashID":190,"executedInteractions":[]},{"hashID":191,"executedInteractions":[]},{"hashID":192,"executedInteractions":[]},{"hashID":193,"executedInteractions":[]},{"hashID":194,"executedInteractions":[]},{"hashID":195,"executedInteractions":[]},{"hashID":196,"executedInteractions":[]},{"hashID":197,"executedInteractions":[]},{"hashID":198,"executedInteractions":[]},{"hashID":199,"executedInteractions":[]},{"hashID":200,"executedInteractions":[]},{"hashID":201,"executedInteractions":[]},{"hashID":202,"executedInteractions":[]},{"hashID":203,"executedInteractions":[]},{"hashID":204,"executedInteractions":[]},{"hashID":205,"executedInteractions":[]},{"hashID":206,"executedInteractions":[]},{"hashID":207,"executedInteractions":[]},{"hashID":208,"executedInteractions":[]},{"hashID":209,"executedInteractions":[]},{"hashID":210,"executedInteractions":[]},{"hashID":211,"executedInteractions":[]},{"hashID":212,"executedInteractions":[]}],"flags":["Interacted With [Cabocla]","Completed Intro","Interacted With [Dungeon Stairs]","ObtainedSplitshot","Interacted With [None]","ObtainedReflexesAndShadowDash","Can Drop Soul Stones","Interacted With [Rescue Cage]","Can Drop Blessed Gear","JabadeFirstTalkDone","Interacted With [Blessed Gear Shop]","Purchased Blessed Weapon","Interacted With [Joao Abade]","Interacted With [Broken Stair]","Interacted With [Skills Book]","Defeated [Jailer_Unique]","Saw Comerciante Flashback","Defeated [Comerciante]","Obtained Wood","CanFixStairs","FixedStairs","Interacted With [Bell]","Interacted With [Reliquary]","Can Drop Relics"],"playerInventorySaveData":{"Items":[{"_relicBaseDefinitionID":0,"_eRelicRarity":3,"_ascended":false,"_upgradeLevel":0,"_affixesData":[{"_relicAffixDefinitionId":135,"_rollValue":1.0,"_tier":1}],"_position":{"x":4,"y":2},"_showNotification":false},{"_relicBaseDefinitionID":0,"_eRelicRarity":3,"_ascended":false,"_upgradeLevel":0,"_affixesData":[{"_relicAffixDefinitionId":143,"_rollValue":1.0,"_tier":1}],"_position":{"x":3,"y":4},"_showNotification":false},{"_relicBaseDefinitionID":0,"_eRelicRarity":3,"_ascended":false,"_upgradeLevel":0,"_affixesData":[{"_relicAffixDefinitionId":145,"_rollValue":1.0,"_tier":1}],"_position":{"x":2,"y":4},"_showNotification":false},{"_relicBaseDefinitionID":0,"_eRelicRarity":3,"_ascended":false,"_upgradeLevel":0,"_affixesData":[{"_relicAffixDefinitionId":88,"_rollValue":1.0,"_tier":1}],"_position":{"x":3,"y":2},"_showNotification":false},{"_relicBaseDefinitionID":0,"_eRelicRarity":3,"_ascended":false,"_upgradeLevel":0,"_affixesData":[{"_relicAffixDefinitionId":139,"_rollValue":1.0,"_tier":1}],"_position":{"x":2,"y":1},"_showNotification":false},{"_relicBaseDefinitionID":0,"_eRelicRarity":3,"_ascended":false,"_upgradeLevel":0,"_affixesData":[{"_relicAffixDefinitionId":148,"_rollValue":1.0,"_tier":1}],"_position":{"x":3,"y":1},"_showNotification":false},{"_relicBaseDefinitionID":0,"_eRelicRarity":3,"_ascended":false,"_upgradeLevel":0,"_affixesData":[{"_relicAffixDefinitionId":144,"_rollValue":1.0,"_tier":1}],"_position":{"x":4,"y":4},"_showNotification":false},{"_relicBaseDefinitionID":0,"_eRelicRarity":3,"_ascended":false,"_upgradeLevel":0,"_affixesData":[{"_relicAffixDefinitionId":94,"_rollValue":1.0,"_tier":1}],"_position":{"x":3,"y":3},"_showNotification":false},{"_relicBaseDefinitionID":60,"_eRelicRarity":2,"_ascended":false,"_upgradeLevel":0,"_affixesData":[{"_relicAffixDefinitionId":126,"_rollValue":1.0,"_tier":1}],"_position":{"x":4,"y":3},"_showNotification":false},{"_relicBaseDefinitionID":0,"_eRelicRarity":3,"_ascended":false,"_upgradeLevel":0,"_affixesData":[{"_relicAffixDefinitionId":141,"_rollValue":1.0,"_tier":1}],"_position":{"x":4,"y":1},"_showNotification":false}]},"externalInventorySaveData":{"ItemPages":[{"Items":[{"_relicBaseDefinitionID":0,"_eRelicRarity":3,"_ascended":false,"_upgradeLevel":0,"_affixesData":[{"_relicAffixDefinitionId":17,"_rollValue":1.0,"_tier":1}],"_position":{"x":0,"y":9},"_showNotification":false},{"_relicBaseDefinitionID":0,"_eRelicRarity":3,"_ascended":false,"_upgradeLevel":0,"_affixesData":[{"_relicAffixDefinitionId":79,"_rollValue":1.0,"_tier":1}],"_position":{"x":1,"y":9},"_showNotification":false},{"_relicBaseDefinitionID":60,"_eRelicRarity":2,"_ascended":false,"_upgradeLevel":0,"_affixesData":[{"_relicAffixDefinitionId":14,"_rollValue":1.0,"_tier":1}],"_position":{"x":6,"y":9},"_showNotification":false},{"_relicBaseDefinitionID":0,"_eRelicRarity":3,"_ascended":false,"_upgradeLevel":0,"_affixesData":[{"_relicAffixDefinitionId":12,"_rollValue":1.0,"_tier":1}],"_position":{"x":1,"y":8},"_showNotification":false},{"_relicBaseDefinitionID":0,"_eRelicRarity":3,"_ascended":false,"_upgradeLevel":0,"_affixesData":[{"_relicAffixDefinitionId":80,"_rollValue":1.0,"_tier":1}],"_position":{"x":2,"y":8},"_showNotification":false},{"_relicBaseDefinitionID":60,"_eRelicRarity":2,"_ascended":false,"_upgradeLevel":0,"_affixesData":[{"_relicAffixDefinitionId":121,"_rollValue":1.0,"_tier":1}],"_position":{"x":5,"y":8},"_showNotification":false},{"_relicBaseDefinitionID":60,"_eRelicRarity":2,"_ascended":false,"_upgradeLevel":0,"_affixesData":[{"_relicAffixDefinitionId":118,"_rollValue":1.0,"_tier":1}],"_position":{"x":6,"y":8},"_showNotification":false},{"_relicBaseDefinitionID":0,"_eRelicRarity":3,"_ascended":false,"_upgradeLevel":0,"_affixesData":[{"_relicAffixDefinitionId":92,"_rollValue":1.0,"_tier":1}],"_position":{"x":0,"y":1},"_showNotification":false},{"_relicBaseDefinitionID":0,"_eRelicRarity":3,"_ascended":false,"_upgradeLevel":0,"_affixesData":[{"_relicAffixDefinitionId":49,"_rollValue":1.0,"_tier":1}],"_position":{"x":1,"y":1},"_showNotification":false},{"_relicBaseDefinitionID":0,"_eRelicRarity":3,"_ascended":false,"_upgradeLevel":0,"_affixesData":[{"_relicAffixDefinitionId":77,"_rollValue":1.0,"_tier":1}],"_position":{"x":2,"y":1},"_showNotification":false},{"_relicBaseDefinitionID":0,"_eRelicRarity":3,"_ascended":false,"_upgradeLevel":0,"_affixesData":[{"_relicAffixDefinitionId":55,"_rollValue":1.0,"_tier":1}],"_position":{"x":3,"y":1},"_showNotification":false},{"_relicBaseDefinitionID":60,"_eRelicRarity":2,"_ascended":false,"_upgradeLevel":0,"_affixesData":[{"_relicAffixDefinitionId":119,"_rollValue":1.0,"_tier":1}],"_position":{"x":6,"y":7},"_showNotification":false},{"_relicBaseDefinitionID":60,"_eRelicRarity":2,"_ascended":false,"_upgradeLevel":0,"_affixesData":[{"_relicAffixDefinitionId":120,"_rollValue":1.0,"_tier":1}],"_position":{"x":6,"y":6},"_showNotification":false},{"_relicBaseDefinitionID":0,"_eRelicRarity":3,"_ascended":false,"_upgradeLevel":0,"_affixesData":[{"_relicAffixDefinitionId":90,"_rollValue":1.0,"_tier":1}],"_position":{"x":0,"y":6},"_showNotification":false},{"_relicBaseDefinitionID":0,"_eRelicRarity":3,"_ascended":false,"_upgradeLevel":0,"_affixesData":[{"_relicAffixDefinitionId":66,"_rollValue":1.0,"_tier":1}],"_position":{"x":2,"y":3},"_showNotification":false},{"_relicBaseDefinitionID":0,"_eRelicRarity":3,"_ascended":false,"_upgradeLevel":0,"_affixesData":[{"_relicAffixDefinitionId":67,"_rollValue":1.0,"_tier":1}],"_position":{"x":3,"y":3},"_showNotification":false},{"_relicBaseDefinitionID":60,"_eRelicRarity":2,"_ascended":false,"_upgradeLevel":0,"_affixesData":[{"_relicAffixDefinitionId":127,"_rollValue":1.0,"_tier":1}],"_position":{"x":6,"y":3},"_showNotification":false},{"_relicBaseDefinitionID":47,"_eRelicRarity":3,"_ascended":false,"_upgradeLevel":0,"_affixesData":[{"_relicAffixDefinitionId":59,"_rollValue":1.0,"_tier":1}],"_position":{"x":0,"y":8},"_showNotification":false},{"_relicBaseDefinitionID":0,"_eRelicRarity":3,"_ascended":false,"_upgradeLevel":0,"_affixesData":[{"_relicAffixDefinitionId":93,"_rollValue":1.0,"_tier":1}],"_position":{"x":1,"y":3},"_showNotification":false},{"_relicBaseDefinitionID":51,"_eRelicRarity":3,"_ascended":false,"_upgradeLevel":1,"_affixesData":[{"_relicAffixDefinitionId":54,"_rollValue":1.0,"_tier":1}],"_position":{"x":0,"y":3},"_showNotification":false},{"_relicBaseDefinitionID":0,"_eRelicRarity":3,"_ascended":false,"_upgradeLevel":0,"_affixesData":[{"_relicAffixDefinitionId":81,"_rollValue":1.0,"_tier":1}],"_position":{"x":2,"y":7},"_showNotification":false},{"_relicBaseDefinitionID":40,"_eRelicRarity":3,"_ascended":false,"_upgradeLevel":0,"_affixesData":[{"_relicAffixDefinitionId":86,"_rollValue":1.0,"_tier":1}],"_position":{"x":1,"y":7},"_showNotification":false},{"_relicBaseDefinitionID":60,"_eRelicRarity":2,"_ascended":false,"_upgradeLevel":0,"_affixesData":[{"_relicAffixDefinitionId":6,"_rollValue":1.0,"_tier":1}],"_position":{"x":5,"y":3},"_showNotification":false},{"_relicBaseDefinitionID":60,"_eRelicRarity":2,"_ascended":false,"_upgradeLevel":0,"_affixesData":[{"_relicAffixDefinitionId":3,"_rollValue":1.0,"_tier":1}],"_position":{"x":6,"y":2},"_showNotification":false},{"_relicBaseDefinitionID":60,"_eRelicRarity":2,"_ascended":false,"_upgradeLevel":0,"_affixesData":[{"_relicAffixDefinitionId":2,"_rollValue":1.0,"_tier":1}],"_position":{"x":5,"y":2},"_showNotification":false},{"_relicBaseDefinitionID":0,"_eRelicRarity":3,"_ascended":false,"_upgradeLevel":0,"_affixesData":[{"_relicAffixDefinitionId":5,"_rollValue":1.0,"_tier":1}],"_position":{"x":4,"y":3},"_showNotification":false},{"_relicBaseDefinitionID":0,"_eRelicRarity":3,"_ascended":false,"_upgradeLevel":0,"_affixesData":[{"_relicAffixDefinitionId":50,"_rollValue":1.0,"_tier":1}],"_position":{"x":4,"y":1},"_showNotification":false},{"_relicBaseDefinitionID":60,"_eRelicRarity":2,"_ascended":false,"_upgradeLevel":0,"_affixesData":[{"_relicAffixDefinitionId":46,"_rollValue":1.0,"_tier":1}],"_position":{"x":5,"y":6},"_showNotification":false},{"_relicBaseDefinitionID":60,"_eRelicRarity":2,"_ascended":false,"_upgradeLevel":0,"_affixesData":[{"_relicAffixDefinitionId":56,"_rollValue":1.0,"_tier":1}],"_position":{"x":6,"y":1},"_showNotification":false},{"_relicBaseDefinitionID":60,"_eRelicRarity":2,"_ascended":false,"_upgradeLevel":0,"_affixesData":[{"_relicAffixDefinitionId":58,"_rollValue":1.0,"_tier":1}],"_position":{"x":5,"y":1},"_showNotification":false},{"_relicBaseDefinitionID":0,"_eRelicRarity":3,"_ascended":false,"_upgradeLevel":0,"_affixesData":[{"_relicAffixDefinitionId":99,"_rollValue":1.0,"_tier":1}],"_position":{"x":3,"y":7},"_showNotification":false},{"_relicBaseDefinitionID":0,"_eRelicRarity":3,"_ascended":false,"_upgradeLevel":0,"_affixesData":[{"_relicAffixDefinitionId":65,"_rollValue":1.0,"_tier":1}],"_position":{"x":0,"y":0},"_showNotification":false},{"_relicBaseDefinitionID":0,"_eRelicRarity":3,"_ascended":false,"_upgradeLevel":0,"_affixesData":[{"_relicAffixDefinitionId":63,"_rollValue":1.0,"_tier":1}],"_position":{"x":1,"y":0},"_showNotification":false},{"_relicBaseDefinitionID":0,"_eRelicRarity":3,"_ascended":false,"_upgradeLevel":0,"_affixesData":[{"_relicAffixDefinitionId":64,"_rollValue":1.0,"_tier":1}],"_position":{"x":2,"y":0},"_showNotification":false},{"_relicBaseDefinitionID":0,"_eRelicRarity":3,"_ascended":false,"_upgradeLevel":0,"_affixesData":[{"_relicAffixDefinitionId":87,"_rollValue":1.0,"_tier":1}],"_position":{"x":1,"y":5},"_showNotification":false},{"_relicBaseDefinitionID":0,"_eRelicRarity":3,"_ascended":false,"_upgradeLevel":0,"_affixesData":[{"_relicAffixDefinitionId":68,"_rollValue":1.0,"_tier":1}],"_position":{"x":0,"y":2},"_showNotification":false},{"_relicBaseDefinitionID":60,"_eRelicRarity":2,"_ascended":false,"_upgradeLevel":0,"_affixesData":[{"_relicAffixDefinitionId":69,"_rollValue":1.0,"_tier":1}],"_position":{"x":4,"y":2},"_showNotification":false},{"_relicBaseDefinitionID":0,"_eRelicRarity":3,"_ascended":false,"_upgradeLevel":0,"_affixesData":[{"_relicAffixDefinitionId":71,"_rollValue":1.0,"_tier":1}],"_position":{"x":1,"y":2},"_showNotification":false},{"_relicBaseDefinitionID":0,"_eRelicRarity":3,"_ascended":false,"_upgradeLevel":0,"_affixesData":[{"_relicAffixDefinitionId":75,"_rollValue":1.0,"_tier":1}],"_position":{"x":3,"y":0},"_showNotification":false},{"_relicBaseDefinitionID":0,"_eRelicRarity":3,"_ascended":false,"_upgradeLevel":0,"_affixesData":[{"_relicAffixDefinitionId":76,"_rollValue":1.0,"_tier":1}],"_position":{"x":4,"y":0},"_showNotification":false},{"_relicBaseDefinitionID":0,"_eRelicRarity":3,"_ascended":false,"_upgradeLevel":0,"_affixesData":[{"_relicAffixDefinitionId":78,"_rollValue":1.0,"_tier":1}],"_position":{"x":5,"y":0},"_showNotification":false},{"_relicBaseDefinitionID":0,"_eRelicRarity":3,"_ascended":false,"_upgradeLevel":0,"_affixesData":[{"_relicAffixDefinitionId":83,"_rollValue":1.0,"_tier":1}],"_position":{"x":2,"y":2},"_showNotification":false},{"_relicBaseDefinitionID":64,"_eRelicRarity":3,"_ascended":false,"_upgradeLevel":0,"_affixesData":[{"_relicAffixDefinitionId":132,"_rollValue":1.0,"_tier":1}],"_position":{"x":0,"y":7},"_showNotification":false},{"_relicBaseDefinitionID":0,"_eRelicRarity":3,"_ascended":false,"_upgradeLevel":0,"_affixesData":[{"_relicAffixDefinitionId":142,"_rollValue":1.0,"_tier":1}],"_position":{"x":6,"y":0},"_showNotification":false},{"_relicBaseDefinitionID":0,"_eRelicRarity":3,"_ascended":false,"_upgradeLevel":0,"_affixesData":[{"_relicAffixDefinitionId":91,"_rollValue":1.0,"_tier":1}],"_position":{"x":0,"y":5},"_showNotification":false},{"_relicBaseDefinitionID":0,"_eRelicRarity":3,"_ascended":false,"_upgradeLevel":0,"_affixesData":[{"_relicAffixDefinitionId":97,"_rollValue":1.0,"_tier":1}],"_position":{"x":2,"y":5},"_showNotification":false}]},{"Items":[{"_relicBaseDefinitionID":60,"_eRelicRarity":2,"_ascended":false,"_upgradeLevel":0,"_affixesData":[{"_relicAffixDefinitionId":130,"_rollValue":1.0,"_tier":1}],"_position":{"x":6,"y":0},"_showNotification":false},{"_relicBaseDefinitionID":60,"_eRelicRarity":2,"_ascended":false,"_upgradeLevel":0,"_affixesData":[{"_relicAffixDefinitionId":129,"_rollValue":1.0,"_tier":1}],"_position":{"x":6,"y":1},"_showNotification":false},{"_relicBaseDefinitionID":0,"_eRelicRarity":3,"_ascended":false,"_upgradeLevel":0,"_affixesData":[{"_relicAffixDefinitionId":95,"_rollValue":1.0,"_tier":1}],"_position":{"x":0,"y":9},"_showNotification":false},{"_relicBaseDefinitionID":60,"_eRelicRarity":2,"_ascended":false,"_upgradeLevel":0,"_affixesData":[{"_relicAffixDefinitionId":123,"_rollValue":1.0,"_tier":1}],"_position":{"x":6,"y":9},"_showNotification":false},{"_relicBaseDefinitionID":60,"_eRelicRarity":2,"_ascended":false,"_upgradeLevel":0,"_affixesData":[{"_relicAffixDefinitionId":125,"_rollValue":1.0,"_tier":1}],"_position":{"x":6,"y":7},"_showNotification":false},{"_relicBaseDefinitionID":46,"_eRelicRarity":3,"_ascended":false,"_upgradeLevel":0,"_affixesData":[{"_relicAffixDefinitionId":89,"_rollValue":1.0,"_tier":1}],"_position":{"x":0,"y":8},"_showNotification":false},{"_relicBaseDefinitionID":0,"_eRelicRarity":3,"_ascended":false,"_upgradeLevel":0,"_affixesData":[{"_relicAffixDefinitionId":98,"_rollValue":1.0,"_tier":1}],"_position":{"x":1,"y":8},"_showNotification":false},{"_relicBaseDefinitionID":60,"_eRelicRarity":2,"_ascended":false,"_upgradeLevel":0,"_affixesData":[{"_relicAffixDefinitionId":61,"_rollValue":1.0,"_tier":1}],"_position":{"x":5,"y":8},"_showNotification":false},{"_relicBaseDefinitionID":0,"_eRelicRarity":3,"_ascended":false,"_upgradeLevel":0,"_affixesData":[{"_relicAffixDefinitionId":96,"_rollValue":1.0,"_tier":1}],"_position":{"x":1,"y":9},"_showNotification":false},{"_relicBaseDefinitionID":60,"_eRelicRarity":2,"_ascended":false,"_upgradeLevel":0,"_affixesData":[{"_relicAffixDefinitionId":128,"_rollValue":1.0,"_tier":1}],"_position":{"x":6,"y":3},"_showNotification":false},{"_relicBaseDefinitionID":60,"_eRelicRarity":2,"_ascended":false,"_upgradeLevel":0,"_affixesData":[{"_relicAffixDefinitionId":131,"_rollValue":1.0,"_tier":1}],"_position":{"x":6,"y":2},"_showNotification":false},{"_relicBaseDefinitionID":60,"_eRelicRarity":2,"_ascended":false,"_upgradeLevel":0,"_affixesData":[{"_relicAffixDefinitionId":124,"_rollValue":1.0,"_tier":1}],"_position":{"x":6,"y":8},"_showNotification":false}]},{"Items":[{"_relicBaseDefinitionID":0,"_eRelicRarity":3,"_ascended":false,"_upgradeLevel":0,"_affixesData":[{"_relicAffixDefinitionId":134,"_rollValue":1.0,"_tier":1}],"_position":{"x":0,"y":9},"_showNotification":false},{"_relicBaseDefinitionID":0,"_eRelicRarity":3,"_ascended":false,"_upgradeLevel":0,"_affixesData":[{"_relicAffixDefinitionId":150,"_rollValue":1.0,"_tier":1}],"_position":{"x":0,"y":7},"_showNotification":false},{"_relicBaseDefinitionID":0,"_eRelicRarity":3,"_ascended":false,"_upgradeLevel":0,"_affixesData":[{"_relicAffixDefinitionId":138,"_rollValue":1.0,"_tier":1}],"_position":{"x":0,"y":6},"_showNotification":false},{"_relicBaseDefinitionID":0,"_eRelicRarity":3,"_ascended":false,"_upgradeLevel":0,"_affixesData":[{"_relicAffixDefinitionId":137,"_rollValue":1.0,"_tier":1}],"_position":{"x":0,"y":3},"_showNotification":false},{"_relicBaseDefinitionID":0,"_eRelicRarity":3,"_ascended":false,"_upgradeLevel":0,"_affixesData":[{"_relicAffixDefinitionId":140,"_rollValue":1.0,"_tier":1}],"_position":{"x":1,"y":7},"_showNotification":false},{"_relicBaseDefinitionID":0,"_eRelicRarity":3,"_ascended":false,"_upgradeLevel":0,"_affixesData":[{"_relicAffixDefinitionId":146,"_rollValue":1.0,"_tier":1}],"_position":{"x":1,"y":6},"_showNotification":false},{"_relicBaseDefinitionID":0,"_eRelicRarity":3,"_ascended":false,"_upgradeLevel":0,"_affixesData":[{"_relicAffixDefinitionId":152,"_rollValue":1.0,"_tier":1}],"_position":{"x":1,"y":9},"_showNotification":false},{"_relicBaseDefinitionID":0,"_eRelicRarity":3,"_ascended":false,"_upgradeLevel":0,"_affixesData":[{"_relicAffixDefinitionId":151,"_rollValue":1.0,"_tier":1}],"_position":{"x":1,"y":3},"_showNotification":false},{"_relicBaseDefinitionID":0,"_eRelicRarity":3,"_ascended":false,"_upgradeLevel":0,"_affixesData":[{"_relicAffixDefinitionId":147,"_rollValue":1.0,"_tier":1}],"_position":{"x":2,"y":3},"_showNotification":false},{"_relicBaseDefinitionID":0,"_eRelicRarity":3,"_ascended":false,"_upgradeLevel":0,"_affixesData":[{"_relicAffixDefinitionId":153,"_rollValue":1.0,"_tier":1}],"_position":{"x":6,"y":2},"_showNotification":false},{"_relicBaseDefinitionID":0,"_eRelicRarity":3,"_ascended":false,"_upgradeLevel":0,"_affixesData":[{"_relicAffixDefinitionId":149,"_rollValue":1.0,"_tier":1}],"_position":{"x":0,"y":5},"_showNotification":false},{"_relicBaseDefinitionID":0,"_eRelicRarity":3,"_ascended":false,"_upgradeLevel":0,"_affixesData":[{"_relicAffixDefinitionId":136,"_rollValue":1.0,"_tier":1}],"_position":{"x":1,"y":5},"_showNotification":false},{"_relicBaseDefinitionID":0,"_eRelicRarity":3,"_ascended":false,"_upgradeLevel":0,"_affixesData":[{"_relicAffixDefinitionId":133,"_rollValue":1.0,"_tier":1}],"_position":{"x":0,"y":8},"_showNotification":false}]}]},"blessedGearData":[{"_gearDefinitionHashId":46,"_multiplier":1.0,"_variantIndex":0},{"_gearDefinitionHashId":130,"_multiplier":0.8220553398132324,"_variantIndex":0},{"_gearDefinitionHashId":19,"_multiplier":0.9021422863006592,"_variantIndex":0},{"_gearDefinitionHashId":9,"_multiplier":0.9319444298744202,"_variantIndex":0},{"_gearDefinitionHashId":13,"_multiplier":0.21559056639671327,"_variantIndex":0},{"_gearDefinitionHashId":21,"_multiplier":0.978191614151001,"_variantIndex":0},{"_gearDefinitionHashId":23,"_multiplier":0.8672324419021606,"_variantIndex":0},{"_gearDefinitionHashId":48,"_multiplier":0.7340731620788574,"_variantIndex":0}],"gameplayTime":1979.61474609375,"bestTime":3.4028234663852887e38,"questsProgressData":[{"QuestDefinitionHashID":0,"CurrentObjectiveIndex":6,"Active":false,"Completed":true},{"QuestDefinitionHashID":1,"CurrentObjectiveIndex":0,"Active":true,"Completed":false},{"QuestDefinitionHashID":2,"CurrentObjectiveIndex":1,"Active":false,"Completed":true},{"QuestDefinitionHashID":3,"CurrentObjectiveIndex":1,"Active":false,"Completed":true},{"QuestDefinitionHashID":4,"CurrentObjectiveIndex":0,"Active":false,"Completed":false},{"QuestDefinitionHashID":5,"CurrentObjectiveIndex":0,"Active":false,"Completed":false},{"QuestDefinitionHashID":6,"CurrentObjectiveIndex":0,"Active":false,"Completed":false},{"QuestDefinitionHashID":7,"CurrentObjectiveIndex":0,"Active":false,"Completed":false},{"QuestDefinitionHashID":8,"CurrentObjectiveIndex":0,"Active":false,"Completed":false},{"QuestDefinitionHashID":9,"CurrentObjectiveIndex":0,"Active":false,"Completed":false},{"QuestDefinitionHashID":10,"CurrentObjectiveIndex":0,"Active":false,"Completed":false},{"QuestDefinitionHashID":11,"CurrentObjectiveIndex":0,"Active":true,"Completed":false}],"greatBellSkillTreeData":{"_skillTreeHashId":5,"_skillTreeNodes":[{"_nodeDefinitionGuid":"d0f3d64b-21ea-4629-af05-d3fb1ce86bcf","_upgradeLevel":3},{"_nodeDefinitionGuid":"3db867e6-b643-40f2-a67b-daa35bcda56d","_upgradeLevel":0},{"_nodeDefinitionGuid":"1ebdc6cc-a2db-41c0-bbfe-5b6ffc94a94c","_upgradeLevel":0},{"_nodeDefinitionGuid":"f21e9503-386c-4784-8920-6b37683382aa","_upgradeLevel":0},{"_nodeDefinitionGuid":"60704617-2a18-45da-8153-564cbb8baa60","_upgradeLevel":0},{"_nodeDefinitionGuid":"9e572201-d750-4aba-911e-50412fa33d67","_upgradeLevel":0},{"_nodeDefinitionGuid":"88671497-e35d-4f63-86e5-83034fc0b633","_upgradeLevel":0},{"_nodeDefinitionGuid":"505cc4e6-9947-4f8b-9043-eba9b9f99b9b","_upgradeLevel":0},{"_nodeDefinitionGuid":"04be78f3-f174-4ec5-8e37-720e5e0a5414","_upgradeLevel":0},{"_nodeDefinitionGuid":"7c1ad4ac-42a5-4db4-8306-df60c9b89cb5","_upgradeLevel":0},{"_nodeDefinitionGuid":"4edab185-0c39-4e8b-817a-a590432faa44","_upgradeLevel":0},{"_nodeDefinitionGuid":"f6e179e1-b34c-4d93-a17c-ec78fbe0d8c0","_upgradeLevel":0},{"_nodeDefinitionGuid":"0a8955a5-0d1e-476a-be34-bfd9b0695f09","_upgradeLevel":0},{"_nodeDefinitionGuid":"2059da83-5dc9-4605-8066-4e3c9cbe5c16","_upgradeLevel":0},{"_nodeDefinitionGuid":"20ab57b7-4470-46db-b8f6-b8ed58a0aeb8","_upgradeLevel":0},{"_nodeDefinitionGuid":"3f5bd689-575a-4ff6-9f70-758b5398a5be","_upgradeLevel":0},{"_nodeDefinitionGuid":"5378b221-027b-4800-892b-31bca6796676","_upgradeLevel":0},{"_nodeDefinitionGuid":"12d4a4b5-28f4-4519-a8d6-0509e8fa4306","_upgradeLevel":0},{"_nodeDefinitionGuid":"95e85915-3aca-44c0-a8eb-eb5825fa4d5b","_upgradeLevel":0},{"_nodeDefinitionGuid":"65131485-bd38-4e81-b33b-f200895c2c4f","_upgradeLevel":0},{"_nodeDefinitionGuid":"e7eaabbe-48a3-4891-8a36-de560da0337f","_upgradeLevel":0},{"_nodeDefinitionGuid":"1c1328e7-6ea6-4115-9ebe-9b6b33216958","_upgradeLevel":0},{"_nodeDefinitionGuid":"1d6062de-1ec2-4ff4-a334-b332955a7717","_upgradeLevel":0},{"_nodeDefinitionGuid":"e8124dd1-e5b8-4098-8b4f-f6ddea99681d","_upgradeLevel":0},{"_nodeDefinitionGuid":"8f843830-6fcc-4e21-919d-7c482e7f261d","_upgradeLevel":1},{"_nodeDefinitionGuid":"aa01d2d7-1bcd-4904-ad71-a504c0fe4ed7","_upgradeLevel":0},{"_nodeDefinitionGuid":"837c13e3-c635-46c2-854e-c98a060c70ee","_upgradeLevel":0},{"_nodeDefinitionGuid":"19459725-dd67-4487-bb53-edda1ae72ed0","_upgradeLevel":0},{"_nodeDefinitionGuid":"b9126093-99da-43a4-8182-50a5ec1cebb7","_upgradeLevel":0},{"_nodeDefinitionGuid":"f759a7f6-372c-4948-9b2d-caf2cb238411","_upgradeLevel":0},{"_nodeDefinitionGuid":"eec1b028-801a-47ce-b1c8-f2548ad929ba","_upgradeLevel":0},{"_nodeDefinitionGuid":"489ced39-aacd-4759-85ad-0da7a2d5af12","_upgradeLevel":0},{"_nodeDefinitionGuid":"e3399eb9-2133-47ef-9383-aa3cbc1dc322","_upgradeLevel":0},{"_nodeDefinitionGuid":"91bd066f-be59-4afb-9f6d-501a71cf1abd","_upgradeLevel":0},{"_nodeDefinitionGuid":"1e24e11f-2110-4fb4-8dd1-cd1fcc0efda0","_upgradeLevel":0},{"_nodeDefinitionGuid":"8e6ca031-fcae-4b97-973f-fd9d0880321b","_upgradeLevel":0},{"_nodeDefinitionGuid":"b2572dfd-bed8-47e5-bc34-3c24c78dc908","_upgradeLevel":0},{"_nodeDefinitionGuid":"51ce2e90-1dba-4322-8ec6-3f6ca5b23192","_upgradeLevel":0},{"_nodeDefinitionGuid":"e0b064c7-2813-4564-a611-3af8991a8cfe","_upgradeLevel":0},{"_nodeDefinitionGuid":"b0b5fc3a-0da8-4043-b231-b718df007d18","_upgradeLevel":0},{"_nodeDefinitionGuid":"66d0ba72-6f3c-4ecb-99d0-cb4dd828b194","_upgradeLevel":0},{"_nodeDefinitionGuid":"98d59b56-f852-4a3b-a9a2-3abbf19a25d0","_upgradeLevel":0},{"_nodeDefinitionGuid":"da8d12bc-693f-4a01-937c-92bc28200232","_upgradeLevel":0},{"_nodeDefinitionGuid":"d9b392cf-5b21-49ae-9544-135d0dfe2d36","_upgradeLevel":0},{"_nodeDefinitionGuid":"ed4b4a7a-c349-49f0-8195-bb9e67b9ec94","_upgradeLevel":0},{"_nodeDefinitionGuid":"ed4d0a8c-3542-4dcf-964f-d02dfa8de950","_upgradeLevel":0},{"_nodeDefinitionGuid":"671a23d0-aabf-4b85-b7bb-90a884d5cc80","_upgradeLevel":0},{"_nodeDefinitionGuid":"6c5148cb-eae2-4c35-b858-30e2dfaaca5d","_upgradeLevel":0},{"_nodeDefinitionGuid":"46edf2e8-4fa0-4266-9c66-30932ead7161","_upgradeLevel":0},{"_nodeDefinitionGuid":"186fe394-57ef-4dde-8d08-4686888c871a","_upgradeLevel":0},{"_nodeDefinitionGuid":"6eb31f18-08b9-473c-ad2b-3d2158a4fcd7","_upgradeLevel":0},{"_nodeDefinitionGuid":"95f60365-e1af-41a2-858d-2599bff240bb","_upgradeLevel":0},{"_nodeDefinitionGuid":"7cc777d2-8fa0-42b1-a177-7586299f0d62","_upgradeLevel":0},{"_nodeDefinitionGuid":"ac59ecdc-1ef1-4356-9be6-ce0cbf6bd7c4","_upgradeLevel":0},{"_nodeDefinitionGuid":"9826759b-1955-49ea-bf1c-1a98043ae12a","_upgradeLevel":0},{"_nodeDefinitionGuid":"add7529c-4993-494a-abe7-ea235d6f9ab0","_upgradeLevel":0},{"_nodeDefinitionGuid":"5fca5078-8167-459d-9d22-ceadd6ec8f98","_upgradeLevel":0},{"_nodeDefinitionGuid":"40dfe5e2-50d1-4159-9b6f-47f067f517a5","_upgradeLevel":0},{"_nodeDefinitionGuid":"761d167c-472e-4a09-9e86-428a81d4c7f4","_upgradeLevel":0},{"_nodeDefinitionGuid":"648493e1-3092-40b4-96c5-3905470cf0da","_upgradeLevel":0},{"_nodeDefinitionGuid":"769b8665-4bb3-428b-b27f-e38b6aa18ab8","_upgradeLevel":0},{"_nodeDefinitionGuid":"616cde37-634f-4fc3-8cb4-6d0b47bfce47","_upgradeLevel":0},{"_nodeDefinitionGuid":"5cdbc0b2-1347-4486-88bd-53a7af827f97","_upgradeLevel":0},{"_nodeDefinitionGuid":"ce380699-b113-4608-a077-6dbc5f923d57","_upgradeLevel":0},{"_nodeDefinitionGuid":"b2c11e1a-fc71-4432-b1cc-da2c847e03a1","_upgradeLevel":0},{"_nodeDefinitionGuid":"9777dece-f232-4da8-a859-1fc0e8469cc6","_upgradeLevel":0},{"_nodeDefinitionGuid":"4bd2afe0-ad4a-472a-b896-ecdaddf505a6","_upgradeLevel":0},{"_nodeDefinitionGuid":"53a89fdb-2f4f-47dc-8538-df629df3095e","_upgradeLevel":0},{"_nodeDefinitionGuid":"ea2f711f-4fdf-42f0-8fc0-7a07198df46d","_upgradeLevel":0},{"_nodeDefinitionGuid":"0d9f1c0e-ba9d-40dc-a039-4c014b51c8d9","_upgradeLevel":0},{"_nodeDefinitionGuid":"8a18debb-b3a8-4184-861d-aa65e70e4cf2","_upgradeLevel":0},{"_nodeDefinitionGuid":"7e0e47a6-dfd0-41a7-a85f-4e7a292e3cd5","_upgradeLevel":0},{"_nodeDefinitionGuid":"c386f915-8dd8-441b-bf39-6543f847ae51","_upgradeLevel":0},{"_nodeDefinitionGuid":"66329d50-8756-4cda-b5c6-a446c970c926","_upgradeLevel":0},{"_nodeDefinitionGuid":"dfe5295f-4044-4ea9-998d-e1f737c2407c","_upgradeLevel":0},{"_nodeDefinitionGuid":"6d43eb7d-4b67-490a-9b61-ca08e2808f44","_upgradeLevel":0},{"_nodeDefinitionGuid":"3e535b03-11e8-4274-a03e-15faa4d555db","_upgradeLevel":0},{"_nodeDefinitionGuid":"05bc7dbf-d828-4221-b0db-61fe2adf9395","_upgradeLevel":0},{"_nodeDefinitionGuid":"3c255a56-067c-4c66-88d4-5b6dae2b51b0","_upgradeLevel":0},{"_nodeDefinitionGuid":"89d2432e-6304-43b3-8665-6a26a2f0dc5f","_upgradeLevel":0}],"_memoryLevel":18,"_memoryLevelOnLastVisit":17,"_totalSoulStones":3040,"_soulsStonesOnLastVisit":2785},"pastRunsData":[{"_runID":1,"_dungeonID":1,"_damageBySkill":{"_serializedList":[{"Key":0,"Value":16500.0}]},"_statCounters":{"_serializedList":[{"Key":"LevelAchieved","Value":1},{"Key":"ShrinesActivated","Value":1},{"Key":"EnemiesDefeated","Value":5},{"Key":"RegularEnemiesDefeated","Value":5},{"Key":"TotalRuns","Value":1},{"Key":"TotalDeaths","Value":0},{"Key":"RunsPerDungeon","Value":0},{"Key":"DeathsInDungeon","Value":0},{"Key":"RunsToCompleteDungeonForTheFirstTime","Value":0}]},"_statAggregators":{"_serializedList":[{"Key":"ExperienceGained","Value":0.0},{"Key":"DamageDealt","Value":16500.0},{"Key":"GameplayTotalTime","Value":46.54144287109375},{"Key":"DungeonBestTime","Value":3.4028234663852887e38},{"Key":"RunTime","Value":46.54144287109375}]},"_statBools":{"_serializedList":[{"Key":"CurrentDungeonCompleted","Value":false}]},"_relicsCollected":{"_serializedList":[]},"_blessedGearCollected":{"_serializedList":[]},"_gearCollected":{"_serializedList":[{"Key":"TrinketsCollected"}]},"_skillBlessings":{"_serializedList":[{"Key":{"m_FileID":12006,"m_PathID":0},"Value":[]},{"Key":{"m_FileID":12004,"m_PathID":0},"Value":[]},{"Key":{"m_FileID":12008,"m_PathID":0},"Value":[]},{"Key":{"m_FileID":12012,"m_PathID":0},"Value":[]}]},"_statBlessings":[],"_banishedBlessings":[],"_eGameOverSource":1},{"_runID":2,"_dungeonID":1,"_damageBySkill":{"_serializedList":[{"Key":211,"Value":398645.309737977},{"Key":0,"Value":68937.78609417625},{"Key":2,"Value":52282.74343327019}]},"_statCounters":{"_serializedList":[{"Key":"LevelAchieved","Value":9},{"Key":"EnemiesDefeated","Value":556},{"Key":"RegularEnemiesDefeated","Value":500},{"Key":"ChampionEnemiesDefeated","Value":4},{"Key":"TotensPurchased","Value":5},{"Key":"EliteEnemiesDefeated","Value":9},{"Key":"SoulStonesCollected","Value":435},{"Key":"UniqueEnemiesDefeated","Value":1},{"Key":"ShrinesActivated","Value":1},{"Key":"RerollsPurchased","Value":2},{"Key":"BossEnemiesDefeated","Value":1},{"Key":"TotalRuns","Value":2},{"Key":"TotalDeaths","Value":0},{"Key":"RunsPerDungeon","Value":2},{"Key":"DeathsInDungeon","Value":0},{"Key":"RunsToCompleteDungeonForTheFirstTime","Value":0}]},"_statAggregators":{"_serializedList":[{"Key":"ExperienceGained","Value":23755.0},{"Key":"DamageDealt","Value":519865.83926542339},{"Key":"GoldGained","Value":7833.0},{"Key":"DamageReceived","Value":2441.5740045905113},{"Key":"GoldSpent","Value":7350.0},{"Key":"GoldSpentOnTotemsPurchased","Value":14400.0},{"Key":"GoldSpentOnReRollsPurchased","Value":1250.0},{"Key":"GameplayTotalTime","Value":267.8087463378906},{"Key":"DungeonBestTime","Value":3.4028234663852887e38},{"Key":"RunTime","Value":221.26730346679688}]},"_statBools":{"_serializedList":[{"Key":"CurrentDungeonCompleted","Value":false}]},"_relicsCollected":{"_serializedList":[{"Key":"RelicsCollected","Value":[{"_relicBaseDefinitionID":7,"_eRelicRarity":0,"_ascended":false,"_upgradeLevel":0,"_affixesData":[{"_relicAffixDefinitionId":26,"_rollValue":0.7510378956794739,"_tier":1},{"_relicAffixDefinitionId":36,"_rollValue":0.1900850385427475,"_tier":1},{"_relicAffixDefinitionId":30,"_rollValue":0.36791694164276125,"_tier":1}],"_position":{"x":2,"y":3},"_showNotification":false},{"_relicBaseDefinitionID":11,"_eRelicRarity":3,"_ascended":false,"_upgradeLevel":0,"_affixesData":[{"_relicAffixDefinitionId":99,"_rollValue":0.0327165387570858,"_tier":1},{"_relicAffixDefinitionId":37,"_rollValue":0.2074979990720749,"_tier":1},{"_relicAffixDefinitionId":1,"_rollValue":0.4285873472690582,"_tier":1},{"_relicAffixDefinitionId":33,"_rollValue":0.8575215935707092,"_tier":1}],"_position":{"x":4,"y":6},"_showNotification":false}]}]},"_blessedGearCollected":{"_serializedList":[{"Key":"BlessedGearCollected"}]},"_gearCollected":{"_serializedList":[{"Key":"TrinketsCollected"}]},"_skillBlessings":{"_serializedList":[{"Key":{"m_FileID":12318,"m_PathID":0},"Value":[{"_rollValue":0.9925639629364014},{"_rollValue":0.16342617571353913},{"_rollValue":0.22870734333992005},{"_rollValue":0.29670336842536929},{"_rollValue":0.6184590458869934},{"_rollValue":0.3626566231250763},{"_rollValue":0.8683876991271973},{"_rollValue":0.17559613287448884}]},{"Key":{"m_FileID":12008,"m_PathID":0},"Value":[]}]},"_statBlessings":[{"_rollValue":0.5515742897987366},{"_rollValue":0.26422956585884097},{"_rollValue":0.7580000162124634},{"_rollValue":0.6445292830467224},{"_rollValue":0.2631073296070099}],"_banishedBlessings":[],"_eGameOverSource":1},{"_runID":3,"_dungeonID":1,"_damageBySkill":{"_serializedList":[{"Key":0,"Value":31292.860502269068}]},"_statCounters":{"_serializedList":[{"Key":"LevelAchieved","Value":5},{"Key":"EnemiesDefeated","Value":60},{"Key":"RegularEnemiesDefeated","Value":48},{"Key":"EliteEnemiesDefeated","Value":2},{"Key":"SoulStonesCollected","Value":50},{"Key":"ShrinesActivated","Value":1},{"Key":"TotalRuns","Value":3},{"Key":"TotalDeaths","Value":0},{"Key":"RunsPerDungeon","Value":3},{"Key":"DeathsInDungeon","Value":0},{"Key":"RunsToCompleteDungeonForTheFirstTime","Value":0}]},"_statAggregators":{"_serializedList":[{"Key":"DamageDealt","Value":31292.860502269068},{"Key":"ExperienceGained","Value":3810.0},{"Key":"GoldGained","Value":1573.0},{"Key":"DamageReceived","Value":330.0},{"Key":"GameplayTotalTime","Value":585.0595703125},{"Key":"DungeonBestTime","Value":3.4028234663852887e38},{"Key":"RunTime","Value":317.2508239746094}]},"_statBools":{"_serializedList":[{"Key":"CurrentDungeonCompleted","Value":false}]},"_relicsCollected":{"_serializedList":[]},"_blessedGearCollected":{"_serializedList":[{"Key":"BlessedGearCollected"}]},"_gearCollected":{"_serializedList":[{"Key":"TrinketsCollected"}]},"_skillBlessings":{"_serializedList":[{"Key":{"m_FileID":12004,"m_PathID":0},"Value":[]}]},"_statBlessings":[],"_banishedBlessings":[],"_eGameOverSource":1},{"_runID":4,"_dungeonID":1,"_damageBySkill":{"_serializedList":[{"Key":0,"Value":51196.95408661455}]},"_statCounters":{"_serializedList":[{"Key":"LevelAchieved","Value":5},{"Key":"EnemiesDefeated","Value":104},{"Key":"RegularEnemiesDefeated","Value":91},{"Key":"EliteEnemiesDefeated","Value":3},{"Key":"SoulStonesCollected","Value":75},{"Key":"RerollsPurchased","Value":2},{"Key":"TotensPurchased","Value":1},{"Key":"TotalRuns","Value":4},{"Key":"TotalDeaths","Value":0},{"Key":"RunsPerDungeon","Value":4},{"Key":"DeathsInDungeon","Value":0},{"Key":"RunsToCompleteDungeonForTheFirstTime","Value":0}]},"_statAggregators":{"_serializedList":[{"Key":"ExperienceGained","Value":3749.0},{"Key":"DamageDealt","Value":51196.95408661455},{"Key":"GoldGained","Value":1376.0},{"Key":"DamageReceived","Value":218.4139416511619},{"Key":"GoldSpent","Value":1200.0},{"Key":"GoldSpentOnReRollsPurchased","Value":800.0},{"Key":"GoldSpentOnTotemsPurchased","Value":600.0},{"Key":"GameplayTotalTime","Value":857.8905029296875},{"Key":"DungeonBestTime","Value":3.4028234663852887e38},{"Key":"RunTime","Value":272.8309020996094}]},"_statBools":{"_serializedList":[{"Key":"CurrentDungeonCompleted","Value":false}]},"_relicsCollected":{"_serializedList":[{"Key":"RelicsCollected","Value":[{"_relicBaseDefinitionID":7,"_eRelicRarity":0,"_ascended":false,"_upgradeLevel":0,"_affixesData":[{"_relicAffixDefinitionId":37,"_rollValue":0.6567794680595398,"_tier":1},{"_relicAffixDefinitionId":36,"_rollValue":0.9421748518943787,"_tier":1},{"_relicAffixDefinitionId":34,"_rollValue":0.8620713949203491,"_tier":1}],"_position":{"x":2,"y":4},"_showNotification":false}]}]},"_blessedGearCollected":{"_serializedList":[]},"_gearCollected":{"_serializedList":[{"Key":"TrinketsCollected"}]},"_skillBlessings":{"_serializedList":[{"Key":{"m_FileID":12112,"m_PathID":0},"Value":[{"_rollValue":0.18613936007022859},{"_rollValue":0.37108829617500307},{"_rollValue":0.7453082203865051},{"_rollValue":0.6621493697166443}]},{"Key":{"m_FileID":12004,"m_PathID":0},"Value":[]}]},"_statBlessings":[{"_rollValue":0.8123284578323364}],"_banishedBlessings":[],"_eGameOverSource":1},{"_runID":5,"_dungeonID":1,"_damageBySkill":{"_serializedList":[{"Key":202,"Value":52439.41776599694},{"Key":203,"Value":178764.7052186462},{"Key":210,"Value":294330.2368168702},{"Key":50,"Value":132515.61313771044},{"Key":0,"Value":67919.91835890146}]},"_statCounters":{"_serializedList":[{"Key":"LevelAchieved","Value":10},{"Key":"EnemiesDefeated","Value":609},{"Key":"RegularEnemiesDefeated","Value":551},{"Key":"EliteEnemiesDefeated","Value":9},{"Key":"SoulStonesCollected","Value":475},{"Key":"ShrinesActivated","Value":3},{"Key":"TotensPurchased","Value":5},{"Key":"UniqueEnemiesDefeated","Value":1},{"Key":"ChampionEnemiesDefeated","Value":7},{"Key":"RerollsPurchased","Value":1},{"Key":"BossEnemiesDefeated","Value":1},{"Key":"TotalRuns","Value":6},{"Key":"TotalDeaths","Value":1},{"Key":"RunsPerDungeon","Value":6},{"Key":"DeathsInDungeon","Value":0},{"Key":"RunsToCompleteDungeonForTheFirstTime","Value":0}]},"_statAggregators":{"_serializedList":[{"Key":"ExperienceGained","Value":39190.0},{"Key":"GoldGained","Value":11155.0},{"Key":"DamageDealt","Value":725969.8912981313},{"Key":"DamageReceived","Value":5514.279581308365},{"Key":"GoldSpent","Value":6950.0},{"Key":"GoldSpentOnTotemsPurchased","Value":15000.0},{"Key":"GoldSpentOnReRollsPurchased","Value":550.0},{"Key":"GameplayTotalTime","Value":1244.078125},{"Key":"DungeonBestTime","Value":3.402823466385289e38},{"Key":"RunTime","Value":264.2222900390625}]},"_statBools":{"_serializedList":[{"Key":"CurrentDungeonCompleted","Value":false}]},"_relicsCollected":{"_serializedList":[{"Key":"RelicsCollected","Value":[{"_relicBaseDefinitionID":61,"_eRelicRarity":0,"_ascended":false,"_upgradeLevel":0,"_affixesData":[{"_relicAffixDefinitionId":122,"_rollValue":0.6934477090835571,"_tier":1},{"_relicAffixDefinitionId":0,"_rollValue":0.8112754225730896,"_tier":1}],"_position":{"x":3,"y":4},"_showNotification":false},{"_relicBaseDefinitionID":63,"_eRelicRarity":2,"_ascended":false,"_upgradeLevel":0,"_affixesData":[{"_relicAffixDefinitionId":125,"_rollValue":0.19513097405433656,"_tier":1},{"_relicAffixDefinitionId":122,"_rollValue":0.0277815330773592,"_tier":1},{"_relicAffixDefinitionId":111,"_rollValue":0.8221230506896973,"_tier":1},{"_relicAffixDefinitionId":38,"_rollValue":0.25365158915519717,"_tier":1},{"_relicAffixDefinitionId":30,"_rollValue":0.5101563334465027,"_tier":1}],"_position":{"x":3,"y":8},"_showNotification":false},{"_relicBaseDefinitionID":12,"_eRelicRarity":3,"_ascended":false,"_upgradeLevel":0,"_affixesData":[{"_relicAffixDefinitionId":66,"_rollValue":0.6391940712928772,"_tier":1},{"_relicAffixDefinitionId":111,"_rollValue":0.7185426950454712,"_tier":1},{"_relicAffixDefinitionId":36,"_rollValue":0.3255966901779175,"_tier":1},{"_relicAffixDefinitionId":33,"_rollValue":0.7433940172195435,"_tier":1}],"_position":{"x":4,"y":4},"_showNotification":false}]}]},"_blessedGearCollected":{"_serializedList":[{"Key":"BlessedGearCollected"}]},"_gearCollected":{"_serializedList":[{"Key":"TrinketsCollected"}]},"_skillBlessings":{"_serializedList":[{"Key":{"m_FileID":12316,"m_PathID":0},"Value":[{"_rollValue":0.7426275610923767},{"_rollValue":0.09151876717805863}]},{"Key":{"m_FileID":12080,"m_PathID":0},"Value":[]},{"Key":{"m_FileID":12304,"m_PathID":0},"Value":[{"_rollValue":0.0046815876848995689},{"_rollValue":0.3280523121356964},{"_rollValue":0.8069713115692139},{"_rollValue":0.74210125207901},{"_rollValue":0.1901419460773468}]}]},"_statBlessings":[{"_rollValue":0.1888379156589508},{"_rollValue":0.8000870943069458},{"_rollValue":0.03429794684052467},{"_rollValue":0.11877657473087311}],"_banishedBlessings":[],"_eGameOverSource":0},{"_runID":6,"_dungeonID":1,"_damageBySkill":{"_serializedList":[{"Key":1,"Value":3857.909587900938},{"Key":210,"Value":71414.72535494426},{"Key":50,"Value":15066.471625163367},{"Key":0,"Value":25500.0}]},"_statCounters":{"_serializedList":[{"Key":"LevelAchieved","Value":5},{"Key":"EnemiesDefeated","Value":166},{"Key":"RegularEnemiesDefeated","Value":153},{"Key":"EliteEnemiesDefeated","Value":2},{"Key":"RerollsPurchased","Value":1},{"Key":"SoulStonesCollected","Value":130},{"Key":"ChampionEnemiesDefeated","Value":2},{"Key":"TotensPurchased","Value":1},{"Key":"UniqueEnemiesDefeated","Value":1},{"Key":"TotalRuns","Value":7},{"Key":"TotalDeaths","Value":2},{"Key":"RunsPerDungeon","Value":7},{"Key":"DeathsInDungeon","Value":1},{"Key":"RunsToCompleteDungeonForTheFirstTime","Value":0}]},"_statAggregators":{"_serializedList":[{"Key":"ExperienceGained","Value":3364.0},{"Key":"GoldGained","Value":1518.0},{"Key":"DamageDealt","Value":115839.1065680079},{"Key":"GoldSpent","Value":750.0},{"Key":"GoldSpentOnReRollsPurchased","Value":150.0},{"Key":"DamageReceived","Value":48.08897376060486},{"Key":"GoldSpentOnTotemsPurchased","Value":600.0},{"Key":"GameplayTotalTime","Value":1394.4658203125},{"Key":"DungeonBestTime","Value":3.402823466385289e38},{"Key":"RunTime","Value":150.3878173828125}]},"_statBools":{"_serializedList":[{"Key":"CurrentDungeonCompleted","Value":false}]},"_relicsCollected":{"_serializedList":[]},"_blessedGearCollected":{"_serializedList":[{"Key":"BlessedGearCollected"}]},"_gearCollected":{"_serializedList":[{"Key":"TrinketsCollected"}]},"_skillBlessings":{"_serializedList":[{"Key":{"m_FileID":12316,"m_PathID":0},"Value":[{"_rollValue":0.9042547941207886},{"_rollValue":0.7980426549911499},{"_rollValue":0.4039258360862732}]},{"Key":{"m_FileID":12080,"m_PathID":0},"Value":[]},{"Key":{"m_FileID":12304,"m_PathID":0},"Value":[{"_rollValue":0.744213879108429}]}]},"_statBlessings":[{"_rollValue":0.49186164140701296}],"_banishedBlessings":[],"_eGameOverSource":0},{"_runID":7,"_dungeonID":1,"_damageBySkill":{"_serializedList":[{"Key":1,"Value":16017.643364330788},{"Key":210,"Value":53528.85192720549},{"Key":50,"Value":43183.1845538807},{"Key":0,"Value":31494.571897361977}]},"_statCounters":{"_serializedList":[{"Key":"LevelAchieved","Value":4},{"Key":"EnemiesDefeated","Value":157},{"Key":"RegularEnemiesDefeated","Value":150},{"Key":"RerollsPurchased","Value":1},{"Key":"EliteEnemiesDefeated","Value":1},{"Key":"SoulStonesCollected","Value":75},{"Key":"UniqueEnemiesDefeated","Value":1},{"Key":"TotalRuns","Value":8},{"Key":"TotalDeaths","Value":3},{"Key":"RunsPerDungeon","Value":8},{"Key":"DeathsInDungeon","Value":2},{"Key":"RunsToCompleteDungeonForTheFirstTime","Value":0}]},"_statAggregators":{"_serializedList":[{"Key":"ExperienceGained","Value":2465.0},{"Key":"GoldGained","Value":2403.0},{"Key":"DamageDealt","Value":144224.2517427799},{"Key":"DamageReceived","Value":0.0},{"Key":"GoldSpent","Value":200.0},{"Key":"GoldSpentOnReRollsPurchased","Value":200.0},{"Key":"GameplayTotalTime","Value":1479.3636474609375},{"Key":"DungeonBestTime","Value":3.402823466385289e38},{"Key":"RunTime","Value":84.89779663085938}]},"_statBools":{"_serializedList":[{"Key":"CurrentDungeonCompleted","Value":false}]},"_relicsCollected":{"_serializedList":[{"Key":"RelicsCollected","Value":[{"_relicBaseDefinitionID":5,"_eRelicRarity":1,"_ascended":false,"_upgradeLevel":0,"_affixesData":[{"_relicAffixDefinitionId":110,"_rollValue":0.04446113854646683,"_tier":1},{"_relicAffixDefinitionId":116,"_rollValue":0.5024778842926025,"_tier":1},{"_relicAffixDefinitionId":0,"_rollValue":0.8647453188896179,"_tier":1},{"_relicAffixDefinitionId":114,"_rollValue":0.8516430854797363,"_tier":1},{"_relicAffixDefinitionId":38,"_rollValue":0.7427434921264648,"_tier":1}],"_position":{"x":4,"y":4},"_showNotification":false}]}]},"_blessedGearCollected":{"_serializedList":[]},"_gearCollected":{"_serializedList":[{"Key":"TrinketsCollected"}]},"_skillBlessings":{"_serializedList":[{"Key":{"m_FileID":12316,"m_PathID":0},"Value":[{"_rollValue":0.13888408243656159},{"_rollValue":0.5912469029426575}]},{"Key":{"m_FileID":12080,"m_PathID":0},"Value":[]},{"Key":{"m_FileID":12304,"m_PathID":0},"Value":[{"_rollValue":0.13511480391025544}]}]},"_statBlessings":[],"_banishedBlessings":[],"_eGameOverSource":0},{"_runID":8,"_dungeonID":1,"_damageBySkill":{"_serializedList":[{"Key":1,"Value":17848.377521630977},{"Key":50,"Value":107337.61036060394},{"Key":210,"Value":82549.4746090425},{"Key":0,"Value":5200.0}]},"_statCounters":{"_serializedList":[{"Key":"LevelAchieved","Value":5},{"Key":"EnemiesDefeated","Value":174},{"Key":"RegularEnemiesDefeated","Value":157},{"Key":"SoulStonesCollected","Value":275},{"Key":"EliteEnemiesDefeated","Value":3},{"Key":"TotensPurchased","Value":1},{"Key":"UniqueEnemiesDefeated","Value":1},{"Key":"TotalRuns","Value":9},{"Key":"TotalDeaths","Value":4},{"Key":"RunsPerDungeon","Value":9},{"Key":"DeathsInDungeon","Value":3},{"Key":"RunsToCompleteDungeonForTheFirstTime","Value":0}]},"_statAggregators":{"_serializedList":[{"Key":"DamageDealt","Value":212935.4624912793},{"Key":"ExperienceGained","Value":4028.0},{"Key":"GoldGained","Value":3274.0},{"Key":"DamageReceived","Value":0.0},{"Key":"GoldSpent","Value":600.0},{"Key":"GoldSpentOnTotemsPurchased","Value":600.0},{"Key":"GameplayTotalTime","Value":1540.908203125},{"Key":"DungeonBestTime","Value":3.402823466385289e38},{"Key":"RunTime","Value":61.54461669921875}]},"_statBools":{"_serializedList":[{"Key":"CurrentDungeonCompleted","Value":false}]},"_relicsCollected":{"_serializedList":[{"Key":"RelicsCollected","Value":[{"_relicBaseDefinitionID":61,"_eRelicRarity":0,"_ascended":false,"_upgradeLevel":0,"_affixesData":[{"_relicAffixDefinitionId":109,"_rollValue":0.12580201029777528,"_tier":1},{"_relicAffixDefinitionId":115,"_rollValue":0.5202221274375916,"_tier":1}],"_position":{"x":3,"y":4},"_showNotification":false}]}]},"_blessedGearCollected":{"_serializedList":[{"Key":"BlessedGearCollected"}]},"_gearCollected":{"_serializedList":[{"Key":"TrinketsCollected"}]},"_skillBlessings":{"_serializedList":[{"Key":{"m_FileID":12316,"m_PathID":0},"Value":[{"_rollValue":0.18736328184604646},{"_rollValue":0.0252155102789402},{"_rollValue":0.37576955556869509}]},{"Key":{"m_FileID":12080,"m_PathID":0},"Value":[]},{"Key":{"m_FileID":12304,"m_PathID":0},"Value":[{"_rollValue":0.2880111038684845}]}]},"_statBlessings":[{"_rollValue":0.6358187794685364}],"_banishedBlessings":[],"_eGameOverSource":0},{"_runID":9,"_dungeonID":1,"_damageBySkill":{"_serializedList":[{"Key":50,"Value":1278378.0034001033},{"Key":210,"Value":4522730.363214248},{"Key":203,"Value":202921.84658886164},{"Key":0,"Value":1484700.0},{"Key":157,"Value":66089.76287514679}]},"_statCounters":{"_serializedList":[{"Key":"LevelAchieved","Value":15},{"Key":"EnemiesDefeated","Value":957},{"Key":"RegularEnemiesDefeated","Value":848},{"Key":"EliteEnemiesDefeated","Value":18},{"Key":"SoulStonesCollected","Value":975},{"Key":"RerollsPurchased","Value":8},{"Key":"UniqueEnemiesDefeated","Value":2},{"Key":"TotensPurchased","Value":5},{"Key":"ShrinesActivated","Value":2},{"Key":"ChampionEnemiesDefeated","Value":13},{"Key":"BossEnemiesDefeated","Value":1},{"Key":"TotalRuns","Value":10},{"Key":"TotalDeaths","Value":4},{"Key":"RunsPerDungeon","Value":10},{"Key":"DeathsInDungeon","Value":4},{"Key":"RunsToCompleteDungeonForTheFirstTime","Value":0}]},"_statAggregators":{"_serializedList":[{"Key":"ExperienceGained","Value":164903.0},{"Key":"DamageDealt","Value":7554819.9760787379},{"Key":"GoldGained","Value":20433.0},{"Key":"GoldSpent","Value":19200.0},{"Key":"GoldSpentOnReRollsPurchased","Value":83550.0},{"Key":"GoldSpentOnTotemsPurchased","Value":19200.0},{"Key":"DamageReceived","Value":59.56249445420394},{"Key":"GameplayTotalTime","Value":1960.9083251953125},{"Key":"DungeonBestTime","Value":3.402823466385289e38},{"Key":"RunTime","Value":420.0000305175781}]},"_statBools":{"_serializedList":[{"Key":"CurrentDungeonCompleted","Value":false}]},"_relicsCollected":{"_serializedList":[{"Key":"RelicsCollected","Value":[{"_relicBaseDefinitionID":63,"_eRelicRarity":0,"_ascended":false,"_upgradeLevel":0,"_affixesData":[{"_relicAffixDefinitionId":37,"_rollValue":0.2779045104980469,"_tier":1},{"_relicAffixDefinitionId":31,"_rollValue":0.6596242189407349,"_tier":1},{"_relicAffixDefinitionId":38,"_rollValue":0.9677380919456482,"_tier":1}],"_position":{"x":3,"y":4},"_showNotification":false},{"_relicBaseDefinitionID":3,"_eRelicRarity":0,"_ascended":false,"_upgradeLevel":0,"_affixesData":[{"_relicAffixDefinitionId":108,"_rollValue":0.5206709504127502,"_tier":1},{"_relicAffixDefinitionId":38,"_rollValue":0.9128810167312622,"_tier":1}],"_position":{"x":3,"y":8},"_showNotification":false},{"_relicBaseDefinitionID":63,"_eRelicRarity":1,"_ascended":false,"_upgradeLevel":0,"_affixesData":[{"_relicAffixDefinitionId":108,"_rollValue":0.7795644402503967,"_tier":1},{"_relicAffixDefinitionId":109,"_rollValue":0.6131346225738525,"_tier":1},{"_relicAffixDefinitionId":38,"_rollValue":0.9807319045066834,"_tier":1},{"_relicAffixDefinitionId":39,"_rollValue":0.8829984664916992,"_tier":1}],"_position":{"x":5,"y":4},"_showNotification":false},{"_relicBaseDefinitionID":7,"_eRelicRarity":0,"_ascended":false,"_upgradeLevel":0,"_affixesData":[{"_relicAffixDefinitionId":117,"_rollValue":0.8881251215934753,"_tier":1},{"_relicAffixDefinitionId":33,"_rollValue":0.49622854590415957,"_tier":1},{"_relicAffixDefinitionId":114,"_rollValue":0.6846814155578613,"_tier":1}],"_position":{"x":0,"y":0},"_showNotification":false},{"_relicBaseDefinitionID":48,"_eRelicRarity":3,"_ascended":false,"_upgradeLevel":0,"_affixesData":[{"_relicAffixDefinitionId":90,"_rollValue":0.673054575920105,"_tier":1},{"_relicAffixDefinitionId":111,"_rollValue":0.4212099611759186,"_tier":1},{"_relicAffixDefinitionId":31,"_rollValue":0.5919275283813477,"_tier":1},{"_relicAffixDefinitionId":1,"_rollValue":0.5343491435050964,"_tier":1}],"_position":{"x":0,"y":2},"_showNotification":false},{"_relicBaseDefinitionID":7,"_eRelicRarity":0,"_ascended":false,"_upgradeLevel":0,"_affixesData":[{"_relicAffixDefinitionId":122,"_rollValue":0.8568989634513855,"_tier":1},{"_relicAffixDefinitionId":33,"_rollValue":0.03826618194580078,"_tier":1},{"_relicAffixDefinitionId":1,"_rollValue":0.13427411019802094,"_tier":1}],"_position":{"x":0,"y":4},"_showNotification":false},{"_relicBaseDefinitionID":42,"_eRelicRarity":3,"_ascended":false,"_upgradeLevel":0,"_affixesData":[{"_relicAffixDefinitionId":88,"_rollValue":0.7506546974182129,"_tier":1},{"_relicAffixDefinitionId":112,"_rollValue":0.555147111415863,"_tier":1},{"_relicAffixDefinitionId":33,"_rollValue":0.014741694554686547,"_tier":1},{"_relicAffixDefinitionId":1,"_rollValue":0.8215688467025757,"_tier":1}],"_position":{"x":4,"y":6},"_showNotification":false}]}]},"_blessedGearCollected":{"_serializedList":[{"Key":"BlessedGearCollected"}]},"_gearCollected":{"_serializedList":[{"Key":"TrinketsCollected"}]},"_skillBlessings":{"_serializedList":[{"Key":{"m_FileID":12316,"m_PathID":0},"Value":[{"_rollValue":0.2956978380680084},{"_rollValue":0.8879812955856323},{"_rollValue":0.28735843300819399},{"_rollValue":0.07268381863832474},{"_rollValue":0.8676842451095581},{"_rollValue":0.840929388999939},{"_rollValue":0.8008674383163452},{"_rollValue":0.20984569191932679}]},{"Key":{"m_FileID":12080,"m_PathID":0},"Value":[]},{"Key":{"m_FileID":12230,"m_PathID":0},"Value":[{"_rollValue":0.24714329838752747}]}]},"_statBlessings":[{"_rollValue":0.06527305394411087},{"_rollValue":0.7777295112609863}],"_banishedBlessings":[],"_eGameOverSource":2}],"unlockedSkills":[0,1,2,3,4,50,67,69,71,74,157,201,203,209,210,211],"availableSkills":[0,1,2,3,4,50,67,69,71,74,157,201,203,209,210,211],"constellationsData":{"interactedForTheFirstTime":false,"availablePoints":0,"skillTreesData":[{"_skillTreeHashId":1,"_skillTreeNodes":[{"_nodeDefinitionGuid":"b7e00616-2bfe-41ce-b5a7-a714782c0f8d","_upgradeLevel":0},{"_nodeDefinitionGuid":"1d67ca9f-2a1f-4a5d-9a0e-1f03ec5c8bbc","_upgradeLevel":0},{"_nodeDefinitionGuid":"ae286d2b-1e92-41a2-9d31-974c74b418f6","_upgradeLevel":0}]},{"_skillTreeHashId":2,"_skillTreeNodes":[{"_nodeDefinitionGuid":"acd9befa-da4c-4056-bb16-13a5a583c4f0","_upgradeLevel":0},{"_nodeDefinitionGuid":"a1821e18-ffa8-45a0-a1c6-3a737014b4fe","_upgradeLevel":0},{"_nodeDefinitionGuid":"52535f87-1acf-4e33-86e8-49b66b17dd73","_upgradeLevel":0},{"_nodeDefinitionGuid":"cafef193-7fdb-4bc4-9995-40428f4be000","_upgradeLevel":0},{"_nodeDefinitionGuid":"04012b7c-e3b0-49a3-8e26-da5b21861606","_upgradeLevel":0}]},{"_skillTreeHashId":3,"_skillTreeNodes":[{"_nodeDefinitionGuid":"f6e8db08-1d4e-4374-a727-d39a42ccacfc","_upgradeLevel":0},{"_nodeDefinitionGuid":"d4edcec5-2ee0-496c-a5fc-076a40977dc7","_upgradeLevel":0},{"_nodeDefinitionGuid":"83eaf03b-f5b3-401d-9e46-1f468be2d2cc","_upgradeLevel":0},{"_nodeDefinitionGuid":"576267f4-9b53-44a8-b0d8-675b01435d6a","_upgradeLevel":0},{"_nodeDefinitionGuid":"b329feb6-1040-4c07-bd2a-76cbc6cff682","_upgradeLevel":0}]},{"_skillTreeHashId":4,"_skillTreeNodes":[{"_nodeDefinitionGuid":"932b7e35-7474-44f4-b591-0db9d0133958","_upgradeLevel":0},{"_nodeDefinitionGuid":"fcebf6a6-e771-4633-88b7-56e112e6db61","_upgradeLevel":0},{"_nodeDefinitionGuid":"51c1ef80-0b65-42b3-ab7c-eaeced8b6189","_upgradeLevel":0},{"_nodeDefinitionGuid":"5efe56ce-ee13-477b-81e0-cd290e40ebbf","_upgradeLevel":0},{"_nodeDefinitionGuid":"2e2b64fa-1bd1-403c-b6ec-58e4411edaa5","_upgradeLevel":0}]},{"_skillTreeHashId":7,"_skillTreeNodes":[]},{"_skillTreeHashId":18,"_skillTreeNodes":[]},{"_skillTreeHashId":16,"_skillTreeNodes":[]},{"_skillTreeHashId":12,"_skillTreeNodes":[]},{"_skillTreeHashId":17,"_skillTreeNodes":[]},{"_skillTreeHashId":11,"_skillTreeNodes":[]},{"_skillTreeHashId":15,"_skillTreeNodes":[]},{"_skillTreeHashId":13,"_skillTreeNodes":[]},{"_skillTreeHashId":14,"_skillTreeNodes":[]}]},"completedOnboardingKeys":["Onboarding Movement","Onboarding Attack","Onboarding Interact","Onboarding First Loop","Onboarding Blessed Gear","Onboarding Blessings","Onboarding Equip Trinket","Onboarding Soul Stones","Notification Wood","Onboarding Great Bell","Onboarding Equip Relic","Onboarding Conviction","Onboarding Low Life"],"lastBlessedShopId":1,"maxTierShownForGearSlot":{"_serializedList":[{"Key":0,"Value":2},{"Key":3,"Value":2},{"Key":2,"Value":2},{"Key":5,"Value":1},{"Key":7,"Value":2},{"Key":8,"Value":1},{"Key":1,"Value":2},{"Key":10,"Value":2},{"Key":6,"Value":2}]},"skillUpgradeLevel":{"_serializedList":[]},"saveVersion":1}